frontend/dist/assets/Arc-R3PUWRPJ-CUdEQO8X.js
frontend/dist/assets/Brave-24BM36UM-C6C5mkTK.js
frontend/dist/assets/Browser-4R4QKTV2-D3ON1q-S.js
frontend/dist/assets/Chrome-TLI42HDP-BgiVz-ma.js
frontend/dist/assets/Edge-AZ34LAFM-EBh9cG_z.js
frontend/dist/assets/Firefox-ZDK7RHKK-5nyhB0sj.js
frontend/dist/assets/Linux-VYP66PDO--MOvpQUa.js
frontend/dist/assets/Macos-5QL4JBJE-DLNYPiln.js
frontend/dist/assets/Opera-BKMCKUXC-CCypmVaM.js
frontend/dist/assets/Safari-PXQIVS6N-B-Lfxb9r.js
frontend/dist/assets/Windows-GTAT3OTE-K9Pt3pUF.js
frontend/dist/assets/ar_AR-OGKOBCOE-C8be8ebk.js
frontend/dist/assets/arbitrum-IA4OWRTN-B0aI2PBQ.js
frontend/dist/assets/assets-NU2OP443-COMs-Mo6.js
frontend/dist/assets/avalanche-MXEFEDSW-DcC5FNt3.js
frontend/dist/assets/base-Z4LFBE5D-DHfqMzJC.js
frontend/dist/assets/blast-TN2WIMWF-BUZNbRBy.js
frontend/dist/assets/bsc-RVE67I5L-DVYEF0vl.js
frontend/dist/assets/ccip-SWlLtw_z.js
frontend/dist/assets/celo-E6XU57FO-C5IguUgF.js
frontend/dist/assets/coinbaseWallet-WWX6LF36-BMRj6mTC.js
frontend/dist/assets/connect-MR6XDLIE-BET5HMNk.js
frontend/dist/assets/create-X4WFHLCW-De9pC3ym.js
frontend/dist/assets/cronos-ROYR77VZ-Prn3LRPZ.js
frontend/dist/assets/es_419-XX7GCEOK-Dv_C7rzZ.js
frontend/dist/assets/ethereum-RFBAMUVK-WsW8NXqo.js
frontend/dist/assets/fr_FR-FQ7DSQ4K-DeWnp2Gj.js
frontend/dist/assets/gnosis-T7U5EW2Q-CoPEM_sI.js
frontend/dist/assets/hardhat-NEEC6JX7-DzuWQYyS.js
frontend/dist/assets/hi_IN-WUORC2ZB-NNGEi4Wk.js
frontend/dist/assets/hooks.module-BybWoRSC.js
frontend/dist/assets/id_ID-NROY6D6K-WS9hlIie.js
frontend/dist/assets/index-BZ9gCaji.js
frontend/dist/assets/index-BnOBClK3.js
frontend/dist/assets/index-C1NT52_0.js
frontend/dist/assets/index-CqaXuDNf.js
frontend/dist/assets/index-FFf4zRP9.js
frontend/dist/assets/index-Oz7fKELe.css
frontend/dist/assets/index.es-DPrH7gt1.js
frontend/dist/assets/inherits_browser-CxSnX98f.js
frontend/dist/assets/ja_JP-5VSMWEEI-BwReBtr2.js
frontend/dist/assets/klaytn-QTDBZIB3-DyuKTpxX.js
st_wallet-0.2.0.dist-info/METADATA
st_wallet-0.2.0.dist-info/WHEEL
st_wallet-0.2.0.dist-info/RECORD
