Metadata-Version: 2.1
Name: st-wallet
Version: 0.2.0
Summary: 
Author: Thomas
Author-email: wxy_000000@qq.com
Requires-Python: >=3.11,<4.0
Classifier: Programming Language :: Python :: 3
Classifier: Programming Language :: Python :: 3.11
Classifier: Programming Language :: Python :: 3.12
Requires-Dist: streamlit (>=1.38.0,<2.0.0)
